splash_screen_ext/__init__.py
splash_screen_ext/_version.py
splash_screen_ext/labextension/build_log.json
splash_screen_ext/labextension/package.json
splash_screen_ext/labextension/schemas/splash-screen-ext/custom-splash.json
splash_screen_ext/labextension/schemas/splash-screen-ext/package.json.orig
splash_screen_ext/labextension/static/51f7e6c3dd70decff99b.gif
splash_screen_ext/labextension/static/52dc626fdcb4852679d6.gif
splash_screen_ext/labextension/static/5de47aa30dc7babf7976.gif
splash_screen_ext/labextension/static/87d748e1cc9818ef9139.gif
splash_screen_ext/labextension/static/a2bfe56fb0c2b12fcbbc.gif
splash_screen_ext/labextension/static/b0e9c40c78e92e9cb243.gif
splash_screen_ext/labextension/static/b43f4cb9262d129f8af3.gif
splash_screen_ext/labextension/static/bd2f9c1349778d71ceec.gif
splash_screen_ext/labextension/static/d07f4a489cb132205fdd.gif
splash_screen_ext/labextension/static/ea03f9aa7a31a955cabd.gif
splash_screen_ext/labextension/static/f875d3d2c07e2f4b6edf.gif
splash_screen_ext/labextension/static/ffcdc15809122262a64d.gif
splash_screen_ext/labextension/static/lib_index_js.d735559f084889851f09.js
splash_screen_ext/labextension/static/lib_index_js.d735559f084889851f09.js.map
splash_screen_ext/labextension/static/remoteEntry.3d1ccaecda5f664d8c61.js
splash_screen_ext/labextension/static/remoteEntry.3d1ccaecda5f664d8c61.js.map
splash_screen_ext/labextension/static/style.js
splash_screen_ext/labextension/static/style_index_js.c918cb8bd6e0d14d7f53.js
splash_screen_ext/labextension/static/style_index_js.c918cb8bd6e0d14d7f53.js.map
splash_screen_ext-1.0.1.data/data/share/jupyter/labextensions/splash-screen-ext/build_log.json
splash_screen_ext-1.0.1.data/data/share/jupyter/labextensions/splash-screen-ext/package.json
splash_screen_ext-1.0.1.data/data/share/jupyter/labextensions/splash-screen-ext/schemas/splash-screen-ext/custom-splash.json
splash_screen_ext-1.0.1.dist-info/METADATA
splash_screen_ext-1.0.1.dist-info/WHEEL
splash_screen_ext-1.0.1.dist-info/licenses/LICENSE
splash_screen_ext-1.0.1.dist-info/RECORD
