Metadata-Version: 2.4
Name: splash_screen_ext
Version: 1.0.1
Summary: A JupyterLab extension.
Project-URL: Homepage, https://github.com/MrCrashLab/splash_screen_ext
Project-URL: Bug Tracker, https://github.com/MrCrashLab/splash_screen_ext/issues
Project-URL: Repository, https://github.com/MrCrashLab/splash_screen_ext.git
Author: buenajen
License: BSD 3-Clause License
License-File: LICENSE
Keywords: jupyter,jupyterlab,jupyterlab-extension
Classifier: Framework :: Jupyter
Classifier: Framework :: Jupyter :: JupyterLab
Classifier: Framework :: Jupyter :: JupyterLab :: 4
Classifier: Framework :: Jupyter :: JupyterLab :: Extensions
Classifier: Framework :: Jupyter :: JupyterLab :: Extensions :: Prebuilt
Classifier: License :: OSI Approved :: BSD License
Classifier: Programming Language :: Python
Classifier: Programming Language :: Python :: 3
Classifier: Programming Language :: Python :: 3.9
Classifier: Programming Language :: Python :: 3.10
Classifier: Programming Language :: Python :: 3.11
Classifier: Programming Language :: Python :: 3.12
Classifier: Programming Language :: Python :: 3.13
Requires-Python: >=3.8
